measure_run_time/__init__.py
measure_run_time/decorators.py
measure_run_time-0.1.0.dist-info/LICENSE.md
measure_run_time-0.1.0.dist-info/METADATA
measure_run_time-0.1.0.dist-info/WHEEL
measure_run_time-0.1.0.dist-info/top_level.txt
measure_run_time-0.1.0.dist-info/RECORD
