Metadata-Version: 2.1
Name: measure_run_time
Version: 0.1.0
Summary: A Python decorator to measure the execution time of functions
Home-page: https://github.com/carlos-paezf/PyPI-Measure_Run_Time-Package
Author: Tu Nombre
Author-email: tu.email@example.com
License: MIT
Classifier: Programming Language :: Python :: 3
Classifier: License :: OSI Approved :: MIT License
Classifier: Operating System :: OS Independent
Requires-Python: >=3.6
License-File: LICENSE.md
